{
	"$schema": "../$schemas/data.schema.json",
	"sku": ["SRM02-05"],
	"name": "Through A Rose Colored Display Link",
	"category": "mission",
	"type": "digital",
	"originalLanguage": "en",
	"description": "Tina, a technomancer, and an independent sprite named Taske, are on a crime spree of attacking corporations that are developing newer security for commlinks and the Matrix. Their weapon is an army of BTL addicts, conditioned to launch agents via an interactive AR program. In their first crime, they pin it on Mafia lieutenant, Dean. The Runners are hired by Don Casquilho, to investigate the crime and bring a little 'family justice' to the criminals.\nAfter figuring out how the crimes are committed, the 'runners then have to deal with Tina and Taske and provide evidence to Don Casquilho of the completed job.",
	"edition": 4,
	"publisher": ["Catalyst Game Labs", "WizKids Games"],
	"releaseDate": ["2006-01-01"],
	"gameDate": "2070-01",
	"status": "ok",
	"cover": "./cover.jpg"
}
