{
	"$schema": "../$schemas/data.schema.json",
	"sku": ["KAGE-07"],
	"name": "KA•GE: Issue 7",
	"category": "magazine",
	"type": "print",
	"originalLanguage": "en",
	"description": "Index:\n1 Front page (Sean Parrack)\n2 Notes from the Net (Editorial, Credits and Index - Jim Long)\n3 Notes from the Net (Letters - Steve Scott)\n4 Paterson's Guide to Paranormal Animals (Gaki, Goblin Spider, Greater Carp - Stephen Kenson)\n10 KA*GE Fiction (A Closer Look - Chad Olson)\n16 Shadows (Former KE Guard, Former KE Decker, Former KE Security Mage archetypes - Brian Walker)\n19 Neo-Anarchist Guide (Australiasia History, Brisbane Sprawl - Craig Gaffney)\n25 Turring's Guide to Organizations (ANZAC - Craig Gaffney)\n27 The Awakened Citizen (Life in Australiasia - Craig Gaffney)\n30 KA*GE Fiction (An Ounce of Prevention - Robert Frager)\n36 Questions and Answers\n40 Paydata\n46 Network Member Graffiti\n47 Writing on the Wall (News from the Shadowrun Universe)\n48 Rear Page",
	"edition": 2,
	"publisher": ["Other"],
	"releaseDate": ["1993-01-01"],
	"gameDate": "2054-01",
	"status": "ok",
	"cover": "./cover.jpg"
}
