{
	"$schema": "../$schemas/data.schema.json",
	"sku": ["27452", "45048"],
	"name": "Book of the Lost",
	"category": "mission",
	"type": "digital",
	"names": { "de-DE": "Buch der Verlorenen" },
	"originalLanguage": "en-US",
	"description": "No Longer Hidden\n\nThe Bastard, upright. A man in clown makeup stands in a broken skyraker window over another man on the verge of a long plummet. Near the clown's hand, a white rose. Opportunity, adventure, but also mania and frenzy. 404, upright. A woman crouches on the edge of a rooftop, holding a white rose. In the distance is the image of a woman in a red dress. Destruction, failure, collapse. Queen of coins. A woman in a red dress, lounging amidst luxury. She has material wealth but emptiness of soul. Upright, she is opulence, magnificent. Inverse is suspense, fear.\nOpportunity and adventure abounds. Destruction and failure loom. Will the result be magnificence—or fear?\nBook of the Lost takes the intricate art of the Sixth World Tarot and turns it into stories and campaigns for Shadowrun players. Full of plot hooks and adventure seeds, this book is a treasure trove of ideas, mysteries, and enigmas that can make memorable games. Open it and explore knowledge that had been lost but is now, here, rediscovered. And waiting for you.",
	"edition": 5,
	"publisher": ["Catalyst Game Labs", "Pegasus Spiele"],
	"releaseDate": ["2017-03-01"],
	"gameDate": "2079-02",
	"status": "ok",
	"cover": "./cover.jpg"
}
